chromasql/__init__.py
chromasql/_ast_nodes.py
chromasql/adapters.py
chromasql/analysis.py
chromasql/cli.py
chromasql/collection_service.py
chromasql/errors.py
chromasql/executor.py
chromasql/explain.py
chromasql/grammar.py
chromasql/multi_collection.py
chromasql/parser.py
chromasql/plan.py
chromasql/planner.py
chromasql/server.py
chromasql-1.4.0.dist-info/METADATA
chromasql-1.4.0.dist-info/WHEEL
chromasql-1.4.0.dist-info/entry_points.txt
chromasql-1.4.0.dist-info/top_level.txt
chromasql-1.4.0.dist-info/RECORD
