Metadata-Version: 2.4
Name: chromasql
Version: 1.4.0
Summary: SQL-like DSL for planning and executing scoped ChromaDB queries.
Author-email: darshitac11 <darshitac11@gmail.com>, cruxcode <swaroopshyam0@gmail.com>
License-Expression: LicenseRef-Proprietary
Project-URL: Repository, https://github.com/GetAdriAI/chromasql
Project-URL: Documentation, https://getadriai.github.io/chromasql
Keywords: chromadb,sql,dsl,vector-search
Classifier: Development Status :: 3 - Alpha
Classifier: Intended Audience :: Developers
Classifier: Programming Language :: Python :: 3
Classifier: Programming Language :: Python :: 3.9
Classifier: Programming Language :: Python :: 3.10
Classifier: Programming Language :: Python :: 3.11
Classifier: Programming Language :: Python :: 3.12
Classifier: Topic :: Database
Classifier: Topic :: Scientific/Engineering :: Artificial Intelligence
Requires-Python: >=3.9
Requires-Dist: lark<2.0,>=1.2
Requires-Dist: fastapi>=0.100.0
Requires-Dist: uvicorn>=0.23.0
Requires-Dist: pyyaml>=6.0
Requires-Dist: mkdocs-macros-plugin<2.0.0,>=1.5.0
Requires-Dist: mkdocs-material<10.0.0,>=9.7.0
